multifruits.cpython-36m-darwin.so
multifruits-0.1.0.dist-info/DESCRIPTION.rst
multifruits-0.1.0.dist-info/METADATA
multifruits-0.1.0.dist-info/RECORD
multifruits-0.1.0.dist-info/WHEEL
multifruits-0.1.0.dist-info/metadata.json
multifruits-0.1.0.dist-info/top_level.txt
