Metadata-Version: 2.0
Name: multifruits
Version: 0.1.0
Summary: Tasty multipart form data parser built with cython.
Home-page: https://github.com/pyrates/multifruits
Author: Pyrates
Author-email: yohan.boniface@data.gouv.fr
License: MIT
Platform: POSIX
Classifier: License :: OSI Approved :: MIT License
Classifier: Intended Audience :: Developers
Classifier: Programming Language :: Python :: 3
Classifier: Operating System :: POSIX
Classifier: Operating System :: MacOS :: MacOS X
Classifier: Environment :: Web Environment
Classifier: Development Status :: 4 - Beta
Provides: multifruits
